hidemysrc/__init__.py
hidemysrc/code.py
hidemysrc-0.0.4.dist-info/WHEEL
hidemysrc-0.0.4.dist-info/METADATA
hidemysrc-0.0.4.dist-info/RECORD
