Metadata-Version: 2.1
Name: hidemysrc
Version: 0.0.4
Summary: Python-based package for encrypting your python source code!
Author: ecriminals
Author-email: bio@fbi.ac
Requires-Python: >=3.10.0,<3.11
Classifier: Programming Language :: Python :: 3
Classifier: Programming Language :: Python :: 3.10
Requires-Dist: Flask (>=2.2.0,<3.0.0)
Requires-Dist: colorama (>=0.4.6,<0.5.0)
Requires-Dist: numpy (>=1.22.2,<2.0.0)
Requires-Dist: pycryptodome (>=3.17,<4.0)
Requires-Dist: replit (>=3.2.4,<4.0.0)
Requires-Dist: urllib3 (>=1.26.12,<2.0.0)
